glitch_this/__init__.py
glitch_this/commandline.py
glitch_this/glitch_this.py
glitch_this-1.0.3.dist-info/LICENSE
glitch_this-1.0.3.dist-info/METADATA
glitch_this-1.0.3.dist-info/WHEEL
glitch_this-1.0.3.dist-info/entry_points.txt
glitch_this-1.0.3.dist-info/top_level.txt
glitch_this-1.0.3.dist-info/RECORD
