Metadata-Version: 2.1
Name: glitch_this
Version: 1.0.3
Summary: A package to glitch images and GIFs, with highly customizable options!
Home-page: https://github.com/TotallyNotChase/Glitch-and-Gif
Author: TotallyNotChase
Author-email: totallynotchase42@gmail.com
Classifier: Programming Language :: Python :: 3
Classifier: License :: OSI Approved :: MIT License
Classifier: Operating System :: OS Independent
Requires-Python: >=3.6
License-File: LICENSE
Requires-Dist: Pillow >=6.2.1
Requires-Dist: numpy >=1.18.1
